{
	"info": {
		"_postman_id": "8a2debba-6e32-4343-9ac7-f626d631c0ee",
		"name": "todo",
		"schema": "https://schema.getpostman.com/json/collection/v2.1.0/collection.json"
	},
	"item": [
		{
			"name": "get-user-todo",
			"request": {
				"method": "GET",
				"header": [],
				"url": {
					"raw": "http://localhost:3500/todo/:userId",
					"protocol": "http",
					"host": [
						"localhost"
					],
					"port": "3500",
					"path": [
						"todo",
						":userId"
					],
					"variable": [
						{
							"key": "userId",
							"value": ""
						}
					]
				}
			},
			"response": []
		},
		{
			"name": "update-user-todo",
			"request": {
				"method": "PUT",
				"header": [],
				"body": {
					"mode": "raw",
					"raw": "{\r\n    \"todo\":\"\"\r\n}",
					"options": {
						"raw": {
							"language": "json"
						}
					}
				},
				"url": {
					"raw": "http://localhost:3500/todo/:userId",
					"protocol": "http",
					"host": [
						"localhost"
					],
					"port": "3500",
					"path": [
						"todo",
						":userId"
					],
					"variable": [
						{
							"key": "userId",
							"value": ""
						}
					]
				}
			},
			"response": []
		},
		{
			"name": "add-user-todo",
			"request": {
				"method": "POST",
				"header": [],
				"body": {
					"mode": "raw",
					"raw": "{\r\n    \"todo\":\"\"\r\n}",
					"options": {
						"raw": {
							"language": "json"
						}
					}
				},
				"url": {
					"raw": "http://localhost:3500/todo/:userId",
					"protocol": "http",
					"host": [
						"localhost"
					],
					"port": "3500",
					"path": [
						"todo",
						":userId"
					],
					"variable": [
						{
							"key": "userId",
							"value": ""
						}
					]
				}
			},
			"response": []
		},
		{
			"name": "delete-user-todo",
			"request": {
				"method": "DELETE",
				"header": [],
				"body": {
					"mode": "raw",
					"raw": "{\r\n    \"todo\":\"\"\r\n}",
					"options": {
						"raw": {
							"language": "json"
						}
					}
				},
				"url": {
					"raw": "http://localhost:3500/todo/:userId",
					"protocol": "http",
					"host": [
						"localhost"
					],
					"port": "3500",
					"path": [
						"todo",
						":userId"
					],
					"variable": [
						{
							"key": "userId",
							"value": ""
						}
					]
				}
			},
			"response": []
		}
	]
}